robofloak/__init__.py
robofloak/api.py
robofloak/pipe.py
robofloak/postprocs.py
robofloak-0.0.2.dist-info/DESCRIPTION.rst
robofloak-0.0.2.dist-info/METADATA
robofloak-0.0.2.dist-info/RECORD
robofloak-0.0.2.dist-info/WHEEL
robofloak-0.0.2.dist-info/metadata.json
robofloak-0.0.2.dist-info/top_level.txt
