Metadata-Version: 2.0
Name: robofloak
Version: 0.0.2
Summary: python client for deploying Roboflow models to OAK devices
Home-page: https://www.roboflow.com
Author: Roboflow
Author-email: jacob@roboflow.com
License: GPLv3+
Platform: UNKNOWN
Classifier: Programming Language :: Python :: 3
Classifier: Operating System :: OS Independent
Requires-Python: >=3.6
Requires-Dist: numpy (==1.22.0)
Requires-Dist: requests (==2.26.0)
